skidy/__init__.py
skidy/__main__.py
skidy/kinematics_generator.py
skidy/matrices.py
skidy/parser.py
skidy/symbols.py
skidy-0.0.1.dist-info/LICENSE
skidy-0.0.1.dist-info/METADATA
skidy-0.0.1.dist-info/WHEEL
skidy-0.0.1.dist-info/entry_points.txt
skidy-0.0.1.dist-info/top_level.txt
skidy-0.0.1.dist-info/RECORD
