Metadata-Version: 2.1
Name: skidy
Version: 0.0.1
Summary: Symbolic kinematics and dynamics model generation using Equations of Motion in closed form.
Author: Underactuated Lab DFKI Robotics Innovation Center Bremen
Maintainer: Hannah Isermann
Maintainer-email: Hannah Isermann <hannah.isermann@dfki.de>
License: BSD 3-Clause License
Project-URL: Repository, https://github.com/dfki-ric-underactuated-lab/skidy
Keywords: symbolic,code generation,robot,kinematics,dynamics,equation of motion
Classifier: Development Status :: 4 - Beta
Classifier: License :: OSI Approved :: BSD License
Classifier: Programming Language :: Python :: 3
Classifier: Operating System :: OS Independent
Requires-Python: >=3.8
License-File: LICENSE
Requires-Dist: numpy
Requires-Dist: sympy >=1.8
Requires-Dist: urdf-parser-py >=0.0.4
Requires-Dist: regex
Requires-Dist: PyYAML
Requires-Dist: pylatex
Requires-Dist: pydot
Provides-Extra: testing
Requires-Dist: cython ; extra == 'testing'
Requires-Dist: oct2py ; extra == 'testing'
Requires-Dist: kinpy ; extra == 'testing'
Requires-Dist: pin ; extra == 'testing'
